dummy.py
potman/__init__.py
potman/feature_store_repo.py
potman/feature_store_repo_factory.py
potman/logging.py
potman/potman_state.py
potman/toolkit.py
potman/cli/__init__.py
potman/cli/controller.py
potman/cli/main.py
potman/cli/model.py
potman/cli/view.py
potman/cli/view_observer.py
potman/cli/actions/__init__.py
potman/cli/actions/action.py
potman/cli/actions/action_type.py
potman/cli/actions/add_feature_store_finish_action.py
potman/cli/actions/add_feature_store_start_action.py
potman/cli/actions/list_feature_stores_action.py
potman/cli/actions/print_config_action.py
potman/cli/actions/print_help_action.py
potman/cli/actions/print_potman_dir_action.py
potman/cli/actions/pull_action.py
potman/cli/actions/quit_action.py
potman/cli/actions/remove_feature_store_action.py
potman/cli/resources/__init__.py
potman/cli/resources/banner.txt
potman/cli/workflows/__init__.py
potman/cli/workflows/add_feature_store_workflow.py
potman/cli/workflows/workflow.py
potman/config/__init__.py
potman/config/feature_store_config.py
potman/config/potman_config.py
potman-0.1.0.dev20230321210953.dist-info/LICENSE
potman-0.1.0.dev20230321210953.dist-info/METADATA
potman-0.1.0.dev20230321210953.dist-info/WHEEL
potman-0.1.0.dev20230321210953.dist-info/entry_points.txt
potman-0.1.0.dev20230321210953.dist-info/top_level.txt
potman-0.1.0.dev20230321210953.dist-info/RECORD
